README.md
setup.cfg
setup.py
configs/config.json
configs/config.txt
configs/config.yml
configs/invalid_config.yaml
shtuka/__init__.py
shtuka/meta.py
shtuka/os.py
shtuka/utils.py
shtuka/wrap.py
shtuka.egg-info/PKG-INFO
shtuka.egg-info/SOURCES.txt
shtuka.egg-info/dependency_links.txt
shtuka.egg-info/requires.txt
shtuka.egg-info/top_level.txt
shtuka/core/__init__.py
shtuka/core/base.py
shtuka/core/composite.py