Metadata-Version: 2.1
Name: shtuka
Version: 0.2.0
Summary: Neat and tidy configs gadget with methods on steroids 🔥
Home-page: https://github.com/stasbel/shtuka
Author: Stanislav Beliaev
Author-email: stasbelyaev96@gmail.com
License: MIT
Download-URL: https://github.com/stasbel/shtuka
Project-URL: Source Code, https://github.com/stasbel/shtuka
Project-URL: Bug Tracker, https://github.com/stasbel/shtuka/issues
Keywords: yaml,json,config,tool,dict
Platform: UNKNOWN
Classifier: Development Status :: 3 - Alpha
Classifier: Intended Audience :: Developers
Classifier: Topic :: Software Development :: Libraries :: Python Modules
Classifier: License :: OSI Approved :: MIT License
Classifier: Operating System :: OS Independent
Classifier: Programming Language :: Python :: 3
Classifier: Programming Language :: Python :: 3.6
Classifier: Programming Language :: Python :: 3.7
Classifier: Programming Language :: Python :: 3.8
Requires-Python: >=3.6
Provides-Extra: format
Provides-Extra: lint
Provides-Extra: test
Provides-Extra: dev
Provides-Extra: all
